gulag/__init__.py
gulag/cache.py
gulag/exception.py
gulag/nosql.py
gulag/utils.py
gulag-0.47.dist-info/DESCRIPTION.rst
gulag-0.47.dist-info/METADATA
gulag-0.47.dist-info/RECORD
gulag-0.47.dist-info/WHEEL
gulag-0.47.dist-info/metadata.json
gulag-0.47.dist-info/top_level.txt
