Metadata-Version: 2.0
Name: gulag
Version: 0.47
Summary: Encapsulation convenience for mongo collections
Home-page: https://bitbucket.org/jorjun/project_gulag
Author: @jorjun
Author-email: jorjuntech@icloud.com
License: Apache License, Version 2.0
Keywords: mongo,mongodb,pymongo
Platform: UNKNOWN
Classifier: Development Status :: 5 - Production/Stable
Classifier: Intended Audience :: Developers
Classifier: License :: OSI Approved :: Apache Software License
Classifier: Operating System :: MacOS :: MacOS X
Classifier: Operating System :: POSIX
Classifier: Programming Language :: Python
Classifier: Programming Language :: Python :: 2.7
Classifier: Programming Language :: Python :: 3
Classifier: Programming Language :: Python :: 3.2
Classifier: Programming Language :: Python :: 3.3
Classifier: Programming Language :: Python :: 3.4
Classifier: Programming Language :: Python :: Implementation :: CPython
Classifier: Programming Language :: Python :: Implementation :: PyPy
Classifier: Topic :: Database
Requires-Dist: httplib2
Requires-Dist: pymongo
